{
    "de_meaning": "Die Hoffnung auf ist der Wunsch oder die Erwartung, dass etwas Positives eintreten wird.",
    "de_meaning_fa": "die Hoffnung auf آرزو یا انتظاری است که چیز مثبتی اتفاق بیفتد.",
    "de_synonyms": [
        "die Zuversicht auf",
        "die Erwartung auf",
        "der Optimismus für"
    ],
    "de_example_1": "Die Hoffnung auf Frieden ist groß.",
    "de_example_fa_1": "امید به صلح زیاد است.",
    "de_example_2": "Ich habe keine Hoffnung auf eine schnelle Lösung.",
    "de_example_fa_2": "من امیدی به راه‌حل سریع ندارم.",
    "fa_meaning": "امید به",
    "en_meaning": "hope for",
    "part_of_speech": "Nomen",
    "article": "die",
    "frequency": "Very common",
    "cefr_level": "B1",
    "perfekt_präteritum": "",
    "is_verb": false,
    "word": "die Hoffnung auf",
    "word_query": "die Hoffnung auf",
    "word_query_expanded": "die Hoffnung auf"
}