{
    "de_meaning": "Die Bewerbung um ist der Prozess oder die Unterlagen, mit denen man sich um eine Stelle oder Position bemüht.",
    "de_meaning_fa": "die Bewerbung um فرآیند یا مدارکی است که با آن برای یک موقعیت یا پست تلاش می‌کنید.",
    "de_synonyms": [
        "das Bewerben um",
        "die Kandidatur für",
        "der Antrag auf"
    ],
    "de_example_1": "Meine Bewerbung um die Stelle war erfolgreich.",
    "de_example_fa_1": "درخواست من برای موقعیت شغلی موفق بود.",
    "de_example_2": "Die Bewerbung um ein Stipendium ist schwierig.",
    "de_example_fa_2": "درخواست برای بورسیه سخت است.",
    "fa_meaning": "درخواست برای",
    "en_meaning": "application for",
    "part_of_speech": "Nomen",
    "article": "die",
    "frequency": "Very common",
    "cefr_level": "B1",
    "perfekt_präteritum": "",
    "is_verb": false,
    "word": "die Bewerbung um",
    "word_query": "die Bewerbung um",
    "word_query_expanded": "die Bewerbung um"
}