{
    "en_meaning": "reward / prize / bonus",
    "frequency": "Fairly common",
    "cefr_level": "B1",
    "part_of_speech": "Noun",
    "de_meaning": "Eine Belohnung ist etwas Schönes, das man bekommt, wenn man etwas Gutes getan hat.",
    "de_synonyms": "Prämie, Lohn, Gage, Entlohnung, Vergütung, Auszeichnung, Anerkennung, Belohnung, Geschenk, Bonus, Gratifikation, Provision, Anreiz, Vorteil",
    "fa_meaning": "پاداش / جایزه / تشویق",
    "de_example_sentence": "Die Belohnung für seine harte Arbeit war ein langer Urlaub.\nDie Belohnung für das Lösen des Rätsels war ein Gutschein.",
    "perfekt_präteritum": "",
    "word": "Belohnung, die, -en",
    "word_query": "Belohnung"
}