{
    "en_meaning": "image caption / picture description",
    "frequency": "Uncommon",
    "cefr_level": "B2",
    "part_of_speech": "Noun",
    "de_meaning": "Eine Bildbeschreibung ist eine Erklärung, was auf einem Bild zu sehen ist.",
    "de_synonyms": "Bildunterschrift, Bildlegende, Bildtext, Abbildungserklärung, Bild erläutern, Beschreibung eines Bildes",
    "fa_meaning": "توصیف تصویر / شرح تصویر / کپشن تصویر",
    "de_example_sentence": "Die Bildbeschreibung enthielt detaillierte Informationen über die Komposition und die dargestellten Personen.\nEine gute Bildbeschreibung sollte sowohl die offensichtlichen als auch die subtilen Details berücksichtigen.",
    "perfekt_präteritum": "",
    "word": "Bildbeschreibung, die, -en",
    "word_query": "Bildbeschreibung",
    "de_example_sentence_fa": "\"توصیف تصویر شامل اطلاعات دقیقی درباره ترکیب‌بندی و افراد نمایش داده شده بود.\nیک توصیف خوب از تصویر باید هم جزئیات آشکار و هم جزئیات ظریف را در نظر بگیرد.\"",
    "de_meaning_fa": "توصیف تصویر، توضیحِ آنچه در یک تصویر قابل مشاهده است می‌باشد."
}