{
    "en_meaning": "health check / general examination",
    "frequency": "Uncommon",
    "cefr_level": "B1",
    "part_of_speech": "Noun",
    "de_meaning": "Ein Check-up ist eine allgemeine Gesundheitsuntersuchung beim Arzt.",
    "de_synonyms": "Gesundheitscheck, Vorsorgeuntersuchung, Routineuntersuchung, Untersuchung, ärztliche Untersuchung, körperliche Untersuchung",
    "fa_meaning": "معاینه دوره‌ای / چکاپ / بازبینی",
    "de_example_sentence": "Ich habe nächste Woche einen Check-up beim Arzt vereinbart.\nNach dem Marathon sollte man sich einen gründlichen Check-up gönnen.",
    "perfekt_präteritum": "",
    "word": "Check-up, der / das, -s ",
    "word_query": "Check-up"
}