{
    "en_meaning": "nevertheless / still / despite that / anyway",
    "frequency": "Fairly common",
    "cefr_level": "B1",
    "part_of_speech": "Adverb",
    "de_meaning": "\"Dennoch\" bedeutet \"trotzdem\".",
    "de_synonyms": "trotzdem, allerdigs, gleichwohl, indes, obgleich, wenngleich, trotz, während, währenddessen, ob, jedoch",
    "fa_meaning": "با این حال / با وجود این / با این وجود / با این همه",
    "de_example_sentence": "Obwohl das Wetter schlecht war, haben wir dennoch einen schönen Ausflug gemacht.\nTrotz seiner Müdigkeit, nahm er dennoch an der Diskussion teil.",
    "perfekt_präteritum": "",
    "word": "dennoch ",
    "word_query": "dennoch",
    "de_example_sentence_fa": "\"با اینکه هوا بد بود، با این حال یک سفر خوب داشتیم.\nبا اینکه خسته بود، با این حال در بحث شرکت کرد.\"",
    "de_meaning_fa": "با این حال، به معنای \"با وجود این\" است."
}