{
    "en_meaning": "filming day / shooting day",
    "frequency": "Uncommon",
    "cefr_level": "B1",
    "part_of_speech": "Noun",
    "de_meaning": "Ein Drehtag ist ein Tag, an dem ein Film oder eine Fernsehsendung gedreht wird.",
    "de_synonyms": "Drehtage, Filmaufnahmen, Aufnahmetage, Drehtermine, Aufnahmetermine",
    "fa_meaning": "فیلمبرداری / روز فیلمبرداری / روز ضبط (if referring specifically to film/video production)",
    "de_example_sentence": "Der Drehtag dauerte länger als erwartet, und die Crew war total erschöpft.\nWir haben den Drehtag mit einem gemütlichen Abendessen zusammen gefeiert.",
    "perfekt_präteritum": "gedreht / drehte",
    "word": "Drehtag, der, -e",
    "word_query": "Drehtag"
}