{
    "en_meaning": "to sleep through the night / to sleep soundly",
    "frequency": "Fairly common",
    "cefr_level": "B1",
    "part_of_speech": "Verb",
    "de_meaning": "\"Durchschlafen\" bedeutet, die ganze Nacht ohne Aufwachen zu schlafen.",
    "de_synonyms": "auslafen, durchlafen, ungestört schlafen, tief schlafen, ruhig schlafen, ohne Unterbrechung schlafen",
    "fa_meaning": "خوابیدن تا صبح / خوابیدن بدون بیدار شدن",
    "de_example_sentence": "Ich konnte letzte Nacht leider nicht durchschlafen, weil die Nachbarn sehr laut waren.\nNach der anstrengenden Wanderung habe ich endlich durchgeschlafen.",
    "perfekt_präteritum": "ge-schlafen / schlief",
    "word": "durch|schlafen, schläft durch, schlief durch, hat durchgeschlafen ",
    "word_query": "durchschlafen"
}