{
    "en_meaning": "to make sense / to be clear / to dawn on someone.",
    "frequency": "Fairly common",
    "cefr_level": "C1",
    "part_of_speech": "Verb",
    "de_meaning": "\"Einleuchten\" bedeutet, dass etwas für jemanden verständlich oder klar wird.",
    "de_synonyms": "ersichtlich sein, klar sein, verständlich sein, nachvollziehbar sein, begreiflich sein, offensichtlich sein, evident sein, sich erschließen, sich aufzeigen, sich abzeichnen",
    "fa_meaning": "فهمیدن / واضح بودن / روشن بودن / قابل درک بودن",
    "de_example_sentence": "Es ist verständlich, warum er so reagiert, wenn man die Situation betrachtet, sie sollte einleuchten.\nDie Komplexität des Problems sollte jedem Fachmann einleuchten, sobald er die Daten analysiert hat.",
    "perfekt_präteritum": "geleuchtet / leuchtete",
    "word": "ein|leuchten ",
    "word_query": "einleuchten"
}