{
    "en_meaning": "basic / fundamental / elemental.",
    "frequency": "Uncommon",
    "cefr_level": "B2",
    "part_of_speech": "Adjective",
    "de_meaning": "\"Elementar\" bedeutet, dass etwas grundlegend und einfach ist.",
    "de_synonyms": "grundlegend, wesentlich, basal, primär, anfänglich, ursprünglich, elementar, einfach, schlicht, primitiv",
    "fa_meaning": "اساسی / بنیادی / عنصری",
    "de_example_sentence": "Die elementare Frage ist, ob wir die Entscheidung jetzt treffen sollen.\nEs war ein elementarer Fehler, der zu dem Unfall führte.",
    "perfekt_präteritum": "geelementarisiert / elementarisierte",
    "word": "elementar ",
    "word_query": "elementar",
    "de_example_sentence_fa": "\"آیا سوال اساسی این است که آیا باید الان این تصمیم را بگیریم؟\nاین یک اشتباه اساسی بود که منجر به تصادف شد.\"",
    "de_meaning_fa": "\"المانتری\" به معنای بنیادی و ساده بودن چیزی است."
}