{
    "en_meaning": "driver / racer / operator",
    "frequency": "Fairly common",
    "cefr_level": "B1",
    "part_of_speech": "Noun",
    "de_meaning": "Ein Fahrer ist jemand, der ein Fahrzeug wie ein Auto oder einen Bus bedient.",
    "de_synonyms": "Lenker, Pilot, Chauffeur, Pilot, Steuermann, Führer, Urheber, Ausführender",
    "fa_meaning": "راننده / رانور / پیشرو",
    "de_example_sentence": "Der LKW-Fahrer war nach der langen Nacht sehr müde.\nEin erfahrener Busfahrer kennt alle Tricks, um den Fahrplan einzuhalten.",
    "perfekt_präteritum": "gefahren / fuhr",
    "word": "Fahrer, der, -",
    "word_query": "Fahrer"
}