{
    "en_meaning": "conversation strategy / communication approach / way of handling a discussion.",
    "frequency": "Uncommon",
    "cefr_level": "C1",
    "part_of_speech": "Noun",
    "de_meaning": "Eine Gesprächsstrategie ist ein Plan, wie du dich in einem Gespräch verhalten willst, um deine Ziele zu erreichen.",
    "de_synonyms": "Kommunikationsstrategie, Gesprächsführung, Verhandlungsstrategie, Diskussionsstrategie, Kommunikationsführung, Gesprächstechnik, Verhandlungsführung, Diskussionsführung, Interaktionsstrategie, Kommunikationsansatz",
    "fa_meaning": "استراتژی گفت‌وگو / راهبرد گفتاری / فنون مذاکره",
    "de_example_sentence": "Die erfolgreiche Verkaufsverhandlung erforderte eine ausgeklügelte Gesprächsstrategie.\nEine klare Gesprächsstrategie hilft, Missverständnisse im Team zu vermeiden.",
    "perfekt_präteritum": "Nicht",
    "word": "Gesprächsstrategie, die, -n",
    "word_query": "Gesprächsstrategie"
}