{
    "en_meaning": "ear, nose, and throat doctor / ent doctor",
    "frequency": "Uncommon",
    "cefr_level": "C2",
    "part_of_speech": "Noun",
    "de_meaning": "Ein Hals-Nasen-Ohrenarzt ist ein Arzt, der sich um Erkrankungen von Hals, Nase und Ohren kümmert.",
    "de_synonyms": "HNO-Arzt, Hals-Nasen-Ohren-Spezialist, Ohrenarzt, Nasenarzt, Halsarzt, Laryngologe, Phoniatre, Otolaryngologe",
    "fa_meaning": "گوش، بینی و گلوپزشک / ENT specialist",
    "de_example_sentence": "Ich habe einen Termin beim Hals-Nasen-Ohrenarzt wegen meiner laufenden Nase.\nMeine Tochter muss zum Hals-Nasen-Ohrenarzt, weil sie ständig an ihren Ohren klagt.",
    "perfekt_präteritum": "",
    "word": "Hals-Nasen-Ohrenarzt, der, &quot;-e",
    "word_query": "Hals-Nasen-Ohrenarzt"
}