{
    "en_meaning": "relating to or involving different cultures / across cultures / multicultural.",
    "frequency": "Fairly common",
    "cefr_level": "C1",
    "part_of_speech": "Adjective",
    "de_meaning": "\"Interkulturell\" bedeutet, dass es um den Umgang und das Verständnis zwischen Menschen aus verschiedenen Kulturen geht.",
    "de_synonyms": "interkulturell, multikulturell, transkulturell, kulturell vielfältig, divers kulturell, international, global",
    "fa_meaning": "بین‌فرهنگی / فرازمینی / میان‌فرهنگی",
    "de_example_sentence": "Die interkulturelle Kommunikation im Team erfordert viel Fingerspitzengefühl.\nWir bieten einen interkulturellen Workshop für Führungskräfte an.",
    "perfekt_präteritum": "",
    "word": "interkulturell ",
    "word_query": "interkulturell"
}