{
    "en_meaning": "to laugh / to smile",
    "frequency": "Very common",
    "cefr_level": "A2",
    "part_of_speech": "Verb",
    "de_meaning": "Lachen bedeutet, wenn man Freude oder etwas Lustiges empfindet und dabei Geräusche von sich gibt und das Gesicht verändert.",
    "de_synonyms": "kichern, grinsen, kichern, spotten, schmunzeln, jauchzen, lachen, feixen, gacker, lachn, treiben, albern sein, necken",
    "fa_meaning": "خندیدن / پوزخند زدن / γελοιοποίηση (rare, mocking laughter)",
    "de_example_sentence": "Sie hat so herzlich gelacht, dass sie Tränen in den Augen hatte.\nIch konnte nicht anders, als über seine alberne Geschichte zu lachen.",
    "perfekt_präteritum": "gelacht / lachte",
    "word": "lachen ",
    "word_query": "lachen"
}