{
    "en_meaning": "easy to read / readable / user-friendly for reading.",
    "frequency": "Uncommon",
    "cefr_level": "B2",
    "part_of_speech": "Adjective",
    "de_meaning": "\"Lesefreundlichen\" bedeutet, dass etwas gut zu lesen ist und angenehm für die Augen.",
    "de_synonyms": "gut lesbar, leicht verständlich, verständlich, zugänglich, klar, anschaulich, übersichtlich, eingängig, anschaulich, aufschlussreich",
    "fa_meaning": "خواندنی / مناسب برای خواندن / با قابلیت خواندن آسان",
    "de_example_sentence": "Die Schriftart ist sehr lesefreundlichen, was das Lesen für Menschen mit Sehschwäche erleichtert.\nDas neue Schulbuch ist mit lesefreundlichen Illustrationen gestaltet, um das Lernen zu fördern.",
    "perfekt_präteritum": "",
    "word": "lesefreundlichen ",
    "word_query": "lesefreundlichen"
}