{
    "en_meaning": "female reader / a woman who reads.",
    "frequency": "Fairly common",
    "cefr_level": "B1",
    "part_of_speech": "Noun",
    "de_meaning": "\"Leserin\" ist eine Frau, die liest.",
    "de_synonyms": "Lesefrau, Bücherleserin, Lektorin, Schriftvorleserin, Textleserin",
    "fa_meaning": "خواننده / مخاطب زن (reader / female audience member)",
    "de_example_sentence": "Die Leserin hat das Buch in einem Zug durchgelesen.\nAls begeisterte Leserin empfiehlt sie dieses historische Roman oft weiter.",
    "perfekt_präteritum": "gelesen / las",
    "word": "Leserin, die, -nen",
    "word_query": "Leserin",
    "de_example_sentence_fa": "\"خواننده، کتاب را یک‌باره خواند.\"\n\"به عنوان یک خواننده مشتاق، او اغلب این رمان تاریخی را به دیگران پیشنهاد می‌کند.\"",
    "de_meaning_fa": "خواننده زن است."
}