{
    "en_meaning": "to operate / to perform surgery.",
    "frequency": "Fairly common",
    "cefr_level": "B2",
    "part_of_speech": "Verb",
    "de_meaning": "\"Operieren\" bedeutet, jemanden im Krankenhaus medizinisch behandeln, meist durch einen Eingriff.",
    "de_synonyms": "chirurgieren, behandeln, eingreifen, durchführen, handhaben, vorgehen, bearbeiten, verfahren, korrigieren, beheben",
    "fa_meaning": "جراحی کردن / عمل کردن / (informal) دست‌کاری کردن",
    "de_example_sentence": "Der Chirurg musste den Patienten dringend operieren, da die Entzündung sich schnell ausbreitete.\nNach der Operation erholte sich mein Großvater überraschend gut und konnte bald wieder nach Hause.",
    "perfekt_präteritum": "geoperiert / operierte",
    "word": "operieren ",
    "word_query": "operieren"
}