{
    "en_meaning": "human resources / personnel department",
    "frequency": "Fairly common",
    "cefr_level": "B2",
    "part_of_speech": "Noun",
    "de_meaning": "Die Personalabteilung kümmert sich in einem Unternehmen um alle Mitarbeiter.",
    "de_synonyms": "Personalwesen, Human Resources, HR, Personalservice, Mitarbeiterabteilung, Mitarbeiterverwaltung, Personalmanagement",
    "fa_meaning": "اداره منابع انسانی / بخش منابع انسانی / امور پرسنلی",
    "de_example_sentence": "Die Personalabteilung hat sich für eine neue Recruiting-Strategie entschieden.\nIch habe meine Bewerbungsunterlagen an die Personalabteilung geschickt.",
    "perfekt_präteritum": "",
    "word": "Personalabteilung, die, -en",
    "word_query": "Personalabteilung"
}