{
    "en_meaning": "postfach means po box / mailbox.",
    "frequency": "Fairly common",
    "cefr_level": "B1",
    "part_of_speech": "Noun",
    "de_meaning": "Ein Postfach ist ein Briefkasten, den man bei der Post mieten kann, um Post zu empfangen.",
    "de_synonyms": "Postfach, Briefkästen, Postfächer, Briefpostfach",
    "fa_meaning": "پست‌باکس / صندوق‌پستی",
    "de_example_sentence": "Ich habe eine neue Adresse und schicke dir meine Postfachnummer gleich.\nUm die Dokumente sicher zu versenden, nutzen wir ein Postfach als Zwischenstation.",
    "perfekt_präteritum": "",
    "word": "Postfach, das, &quot;-er",
    "word_query": "Postfach",
    "de_example_sentence_fa": "\"من آدرس جدیدی دارم و شماره صندوق پستی‌ام را همین الان برات می‌فرستم.\nبرای ارسال امن مدارک، از یک صندوق پستی به عنوان یک مرحله واسط استفاده می‌کنیم.\"",
    "de_meaning_fa": "یک پُست‌بُکس، جعبه‌ای است که می‌توان از اداره‌ی پست اجاره کرد تا نامه دریافت نمود."
}