{
    "en_meaning": "a follow-up question / a request for clarification.",
    "frequency": "Uncommon",
    "cefr_level": "B2",
    "part_of_speech": "Noun",
    "de_meaning": "Eine Rückfrage ist eine Frage, die man stellt, um etwas zu überprüfen oder genauer zu verstehen.",
    "de_synonyms": "Nachfrage, Rückanfrage, Rückmeldung, Anfrage, Erkundigung, Abfrage, Auskunftserfrage",
    "fa_meaning": "بازپرسیدن / پیگیری / استعلام",
    "de_example_sentence": "Ich benötige eine Rückfrage bezüglich meiner letzten Bestellung.\nFür weitere Details benötige ich eine Rückfrage beim Projektleiter.",
    "perfekt_präteritum": "ist zurückgefragt / fragte zurück",
    "word": "Rückfrage, die, -n",
    "word_query": "Rückfrage"
}