{
    "en_meaning": "whisk / snow brush",
    "frequency": "Fairly common",
    "cefr_level": "B1",
    "part_of_speech": "Noun",
    "de_meaning": "Ein Schneebesen ist ein Küchengerät zum Aufschlagen von Sahne oder Eiern.",
    "de_synonyms": "Quirl, Schneevorlage, Rührbesen, Eierschneebesen, Handquirl",
    "fa_meaning": "همزن دستی / همزن سیم‌پیچ (hand mixer / whisk)",
    "de_example_sentence": "Ich habe einen neuen Schneebesen gekauft, weil der alte schon ganz verbogen war.\nUm den Biskuitteig richtig zu verrühren, sollte man einen Schneebesen verwenden.",
    "perfekt_präteritum": "",
    "word": "Schneebesen, der, -",
    "word_query": "Schneebesen",
    "de_example_sentence_fa": "\"من یک همزن دستی جدید خریدم، چون همزن قبلی خیلی خم شده بود.\nبرای مخلوط کردن درست خمیر کیک بیفینگ، باید از همزن دستی استفاده کرد.\"",
    "de_meaning_fa": "همزن دستی وسیله‌ای آشپزخانه برای هم زدن خامه یا تخم‌مرغ است."
}