{
    "en_meaning": "such / like that",
    "frequency": "Uncommon",
    "cefr_level": "B1",
    "part_of_speech": "Adjective",
    "de_meaning": "\"Solch\" ist eine kurze Form von \"so ein\" oder \"so eine\" und wird verwendet, um etwas zu beschreiben, das man schon kennt oder erwähnt hat.",
    "de_synonyms": "solche, solche, solch, solches, solchem, solchem",
    "fa_meaning": "چنین / چنین‌گونه / این‌چنینی",
    "de_example_sentence": "Solch ein Verhalten ist inakzeptabel.\nIch habe noch nie solch eine schöne Landschaft gesehen.",
    "perfekt_präteritum": "",
    "word": "solch ",
    "word_query": "solch"
}