{
    "en_meaning": "trade / goods traffic / commodity flow",
    "frequency": "Uncommon",
    "cefr_level": "B2",
    "part_of_speech": "Noun",
    "de_meaning": "\"Warenverkehr\" bedeutet den Austausch von Gütern zwischen verschiedenen Personen oder Unternehmen.",
    "de_synonyms": "Handelsverkehr, Güterverkehr, Warenfluss, Handelsaustausch, Güteraustausch, Wirtschaftsverkehr",
    "fa_meaning": "تجارت کالا / مبادلات کالا / ترافیک کالا",
    "de_example_sentence": "Der Warenverkehr zwischen den Ländern ist durch neue Handelsabkommen deutlich vereinfacht worden.\nDie steigenden Transportkosten haben den Warenverkehr in einigen Regionen erheblich verlangsamt.",
    "perfekt_präteritum": "",
    "word": "Warenverkehr, der (Sg.)",
    "word_query": "Warenverkehr"
}