{
    "en_meaning": "to wish / to desire / to want",
    "frequency": "Fairly common",
    "cefr_level": "B1",
    "part_of_speech": "Verb",
    "de_meaning": "\"Wünschen\" bedeutet, dass man sich etwas für jemanden oder sich selbst hofft und gerne hätte.",
    "de_synonyms": "begehren, begehrenswert finden, hoffen, wünschen, hoffen, erwarten, ersehnen, begehren, verlangen, sich wünschen, erwarten, anstreben, angestrebt haben",
    "fa_meaning": "آرزو کردن / خواستن / تمنا کردن",
    "de_example_sentence": "Ich wünsche meiner Familie alles Gute zum Geburtstag.\nWir wünschen Ihnen viel Erfolg bei Ihrem neuen Projekt.",
    "perfekt_präteritum": "gewünscht / wünschte",
    "word": "wünschen (sich) ",
    "word_query": "wünschen",
    "de_example_sentence_fa": "\"من برای خانواده‌ام بهترین‌ها را برای روز تولدشان می‌خواهم.\nما برای پروژه جدیدتان آرزوی موفقیت فراوان داریم.\"",
    "de_meaning_fa": "\"خواستن\" به معنای آرزو کردن چیزی برای شخص دیگری یا برای خودتان است."
}