{
    "en_meaning": "at least / even if / at the very least",
    "frequency": "Fairly common",
    "cefr_level": "B1",
    "part_of_speech": "Adverb",
    "de_meaning": "\"Zumindest\" bedeutet, dass etwas zwar nicht perfekt ist, aber trotzdem einen positiven Aspekt hat.",
    "de_synonyms": "mindestens, wenigstens, zumindest, jedenfalls, mindestens, doch, obschon, wenigstens",
    "fa_meaning": "حداقل / دست‌کم / لااقل",
    "de_example_sentence": "Zumindest habe ich versucht, die Aufgabe so gut wie möglich zu lösen.\nZumindest kann man jetzt sagen, dass die Situation sich verbessert hat.",
    "perfekt_präteritum": "",
    "word": "zumindest ",
    "word_query": "zumindest"
}