{
    "en_meaning": "to gain/increase/grow/put on (weight).",
    "frequency": "Fairly common",
    "cefr_level": "B1",
    "part_of_speech": "Verb",
    "de_meaning": "\"Zunehmen\" bedeutet, dicker oder schwerer zu werden.",
    "de_synonyms": "steigern, wachsen, ansteigen, zulegen, aufnehmen, hinzugewinnen, verstärken, erhöhen, ausweiten, expandieren, gedeihen, anschwellen, aufblühen, anwachsen, aufstocken",
    "fa_meaning": "افزودن / چاق شدن / پیشرفت کردن / افزایش یافتن",
    "de_example_sentence": "Er hat in letzter Zeit ein paar Kilo zugenommen, weil er weniger Sport macht.\nDie Firma musste ihren Gewinn im letzten Quartal stark zugenommen.",
    "perfekt_präteritum": "genommen / nahm",
    "word": "zu|nehmen, nimmt zu, nahm zu, hat zugenommen",
    "word_query": "zunehmen"
}