{
    "de_meaning": "Ein Tor ist ein großer Eingang in einer Mauer oder einem Zaun. Man kann durch das Tor gehen oder fahren. Im Sport ist das Tor das Ziel, in das der Ball kommen soll.",
    "de_meaning_fa": "در ساده‌ترین حالت، «تور» یک ورودی بزرگ در دیوار یا حصار است. مردم می‌توانند از طریق تور عبور کنند. در ورزش، تور هدفی است که توپ باید وارد آن شود.",
    "de_synonyms": [
        "Eingang",
        "Pforte",
        "Tür"
    ],
    "de_example_1": "Das Tor zum Garten ist offen.",
    "de_example_fa_1": "دروازه باغ باز است.",
    "de_example_2": "Im Fußball schoss er ein Tor.",
    "de_example_fa_2": "او در فوتبال یک گل زد.",
    "fa_meaning": "دروازه، گل (در ورزش)",
    "en_meaning": "gate, goal (in sports)",
    "part_of_speech": "Substantiv",
    "article": "das",
    "frequency": "Very common",
    "cefr_level": "A1",
    "perfekt_präteritum": "",
    "is_verb": false,
    "word": "das Tor, -e",
    "word_query": "das Tor"
}