{
    "de_meaning": "Ein Gehweg ist ein Weg an der Seite der Straße, auf dem Menschen zu Fuß gehen können.",
    "de_meaning_fa": "پیاده‌رو راهی در کنار خیابان است که مردم می‌توانند روی آن پیاده بروند.",
    "de_synonyms": [
        "der Bürgersteig",
        "der Fußweg",
        "der Trottoir"
    ],
    "de_example_1": "Die Kinder laufen auf dem Gehweg zur Schule.",
    "de_example_fa_1": "کودکان از روی پیاده‌رو به مدرسه می‌روند.",
    "de_example_2": "Bitte fahre nicht mit dem Fahrrad auf dem Gehweg.",
    "de_example_fa_2": "لطفاً با دوچرخه روی پیاده‌رو حرکت نکن.",
    "fa_meaning": "پیاده‌رو",
    "en_meaning": "sidewalk, pavement",
    "part_of_speech": "Substantiv",
    "article": "der",
    "frequency": "Very common",
    "cefr_level": "A1",
    "perfekt_präteritum": "",
    "is_verb": false,
    "word": "der Gehweg, -e",
    "word_query": "der Gehweg"
}