{
    "de_meaning": "Die Sucherei bedeutet, dass man lange und oft erfolglos nach etwas sucht. Es beschreibt das ständige oder mühsame Suchen.",
    "de_meaning_fa": "سوشِرای به این معنی است که کسی مدت طولانی و اغلب بدون موفقیت دنبال چیزی می‌گردد. این واژه جستجوی مداوم یا سخت را توصیف می‌کند.",
    "de_synonyms": [
        "das Suchen",
        "die Suchaktion",
        "die Suche"
    ],
    "de_example_1": "Die Sucherei nach meinen Schlüsseln hat eine halbe Stunde gedauert.",
    "de_example_fa_1": "جستجوی من برای کلیدهایم نیم ساعت طول کشید.",
    "de_example_2": "Ich habe genug von der ständigen Sucherei nach meinen Sachen.",
    "de_example_fa_2": "از جستجوی مداوم وسایلم خسته شده‌ام.",
    "fa_meaning": "جستجوگری مداوم، جستجو کردن طولانی و خسته‌کننده",
    "en_meaning": "the constant or tiresome searching; the act of searching for something for a long time",
    "part_of_speech": "Substantiv",
    "article": "die",
    "frequency": "Uncommon",
    "cefr_level": "B2",
    "perfekt_präteritum": "",
    "is_verb": false,
    "word": "die Sucherei (Sg)",
    "word_query": "die Sucherei"
}