{
    "de_meaning": "Zukunftsmusik bedeutet, dass etwas nur eine Idee für die Zukunft ist und noch nicht passiert ist.",
    "de_meaning_fa": "زukunftsmusik یعنی چیزی فقط یک ایده برای آینده است و هنوز اتفاق نیفتاده است.",
    "de_synonyms": [
        "Zukunftsvision",
        "Traum",
        "Wunschdenken"
    ],
    "de_example_1": "Ein Leben auf dem Mars ist heute noch Zukunftsmusik.",
    "de_example_fa_1": "زندگی روی مریخ امروزه هنوز فقط یک ایده برای آینده است.",
    "de_example_2": "Fliegende Autos sind für viele Menschen noch Zukunftsmusik.",
    "de_example_fa_2": "ماشین‌های پرنده برای بسیاری از مردم هنوز فقط یک ایده برای آینده هستند.",
    "fa_meaning": "آینده‌نگری، چیزی که فقط در آینده ممکن است اتفاق بیفتد.",
    "en_meaning": "Something that is only an idea or plan for the future and has not happened yet.",
    "part_of_speech": "Substantiv",
    "article": "die",
    "frequency": "Uncommon",
    "cefr_level": "B2",
    "perfekt_präteritum": "",
    "is_verb": false,
    "word": "die Zukunftsmusik (Sg.)",
    "word_query": "die Zukunftsmusik"
}