{
    "de_meaning": "Eine Begabung ist, wenn jemand etwas besonders gut kann, zum Beispiel gut malen, singen oder rechnen.",
    "de_meaning_fa": "استعداد یعنی وقتی کسی در انجام کاری خیلی خوب است، مثلاً خوب نقاشی می‌کشد، آواز می‌خواند یا حساب می‌کند.",
    "de_synonyms": [
        "das Talent",
        "die Fähigkeit",
        "die Gabe"
    ],
    "de_example_1": "Anna hat eine große Begabung für Musik.",
    "de_example_fa_1": "آنا استعداد زیادی در موسیقی دارد.",
    "de_example_2": "Seine Begabung im Zeichnen ist beeindruckend.",
    "de_example_fa_2": "استعداد او در نقاشی قابل توجه است.",
    "fa_meaning": "استعداد",
    "en_meaning": "talent, aptitude, gift",
    "part_of_speech": "Substantiv",
    "article": "die",
    "frequency": "Fairly common",
    "cefr_level": "B1",
    "perfekt_präteritum": "",
    "is_verb": false,
    "word": "die Begabung, -e",
    "word_query": "die Begabung"
}