{
    "de_meaning": "Netiquette sind die Regeln für gutes und höfliches Verhalten im Internet, zum Beispiel in E-Mails oder Foren.",
    "de_meaning_fa": "نتیکت قوانین رفتار خوب و مودبانه در اینترنت است، مثلا در ایمیل‌ها یا انجمن‌ها.",
    "de_synonyms": [
        "Online-Benimmregeln",
        "Internet-Etikette",
        "Verhaltensregeln im Netz"
    ],
    "de_example_1": "Man sollte immer die Netiquette beachten, wenn man im Internet schreibt.",
    "de_example_fa_1": "هنگام نوشتن در اینترنت همیشه باید نتیکت را رعایت کرد.",
    "de_example_2": "Die Netiquette hilft, Missverständnisse im Chat zu vermeiden.",
    "de_example_fa_2": "نتیکت کمک می‌کند تا از سوء تفاهم‌ها در چت جلوگیری شود.",
    "fa_meaning": "آداب معاشرت در اینترنت، قوانین رفتار مودبانه در فضای مجازی",
    "en_meaning": "Netiquette means the rules for polite and respectful behavior on the internet.",
    "part_of_speech": "Substantiv",
    "article": "die",
    "frequency": "Fairly common",
    "cefr_level": "B1",
    "perfekt_präteritum": "",
    "is_verb": false,
    "word": "die Netiquette (Sg.)",
    "word_query": "die Netiquette"
}