{
    "de_meaning": "Dramatisch bedeutet, dass etwas sehr aufregend, spannend oder ernst ist und oft starke Gefühle auslöst.",
    "de_meaning_fa": "دراماتیک یعنی چیزی بسیار هیجان‌انگیز، پرتنش یا جدی است و اغلب احساسات قوی ایجاد می‌کند.",
    "de_synonyms": [
        "aufregend",
        "spannend",
        "ernst"
    ],
    "de_example_1": "Die Situation war sehr dramatisch.",
    "de_example_fa_1": "وضعیت بسیار دراماتیک بود.",
    "de_example_2": "Der Film hatte ein dramatisches Ende.",
    "de_example_fa_2": "فیلم یک پایان دراماتیک داشت.",
    "fa_meaning": "دراماتیک، هیجان‌انگیز، پرتنش، جدی",
    "en_meaning": "dramatic, exciting, serious",
    "part_of_speech": "Adjektiv",
    "article": "",
    "frequency": "Very common",
    "cefr_level": "B1",
    "perfekt_präteritum": "",
    "is_verb": false,
    "word": "dramatisch",
    "word_query": "dramatisch"
}