{
    "de_meaning": "Konsumieren bedeutet, etwas zu essen, zu trinken oder zu benutzen.",
    "de_meaning_fa": "مصرف کردن یعنی چیزی را خوردن، نوشیدن یا استفاده کردن.",
    "de_synonyms": [
        "verbrauchen",
        "aufnehmen",
        "einnehmen"
    ],
    "de_example_1": "Wir konsumieren jeden Tag Wasser.",
    "de_example_fa_1": "ما هر روز آب مصرف می‌کنیم.",
    "de_example_2": "Zu viel Zucker zu konsumieren ist ungesund.",
    "de_example_fa_2": "مصرف زیاد شکر ناسالم است.",
    "fa_meaning": "مصرف کردن",
    "en_meaning": "to consume",
    "part_of_speech": "Verb",
    "article": "",
    "frequency": "Fairly common",
    "cefr_level": "B1",
    "perfekt_präteritum": "haben + konsumiert / konsumierte",
    "is_verb": true,
    "word": "konsumieren",
    "word_query": "konsumieren"
}