{
    "de_meaning": "Leiten bedeutet, dass man eine Gruppe oder eine Veranstaltung organisiert und dafür sorgt, dass alles gut abläuft.",
    "de_meaning_fa": "Leiten یعنی اینکه کسی یک گروه یا یک رویداد را سازماندهی می‌کند و مراقب است که همه چیز خوب پیش برود.",
    "de_synonyms": [
        "führen",
        "organisieren",
        "managen"
    ],
    "de_example_1": "Sie leitet das Treffen heute Abend.",
    "de_example_fa_1": "او جلسه امشب را اداره می‌کند.",
    "de_example_2": "Er leitet eine große Firma.",
    "de_example_fa_2": "او یک شرکت بزرگ را مدیریت می‌کند.",
    "fa_meaning": "اداره کردن، مدیریت کردن، رهبری کردن",
    "en_meaning": "to lead, to manage, to conduct",
    "part_of_speech": "Verb",
    "article": "",
    "frequency": "Very common",
    "cefr_level": "B1",
    "perfekt_präteritum": "haben + geleitet / leitete",
    "is_verb": true,
    "word": "leiten (eine Veranstaltung leiten)",
    "word_query": "leiten"
}