{
    "de_meaning": "Etwas voranbringen bedeutet, dafür zu sorgen, dass etwas besser oder schneller wird. Man hilft dabei, dass etwas Fortschritte macht.",
    "de_meaning_fa": "پیش بردن چیزی یعنی کمک کردن به بهتر یا سریع‌تر شدن آن. یعنی باعث پیشرفت چیزی شدن.",
    "de_synonyms": [
        "fördern",
        "weiterentwickeln",
        "unterstützen"
    ],
    "de_example_1": "Wir wollen das Projekt gemeinsam voranbringen.",
    "de_example_fa_1": "ما می‌خواهیم این پروژه را با هم پیش ببریم.",
    "de_example_2": "Neue Ideen bringen die Firma voran.",
    "de_example_fa_2": "ایده‌های جدید شرکت را پیش می‌برند.",
    "fa_meaning": "پیش بردن، ارتقا دادن",
    "en_meaning": "to advance, to promote, to further",
    "part_of_speech": "Verb",
    "article": "",
    "frequency": "Fairly common",
    "cefr_level": "B2",
    "perfekt_präteritum": "hat vorangebracht / brachte voran",
    "is_verb": true,
    "word": "voranbringen (bringt voran, brachte voran, hat voran gebracht)",
    "word_query": "voranbringen"
}