{
    "de_meaning": "Öffentliche Gelder sind das Geld, das vom Staat oder von der Stadt gesammelt und für alle Menschen genutzt wird.",
    "de_meaning_fa": "پول‌های عمومی پول‌هایی هستند که توسط دولت یا شهر جمع‌آوری می‌شوند و برای همه مردم استفاده می‌شوند.",
    "de_synonyms": [
        "Staatsgelder",
        "Steuergelder",
        "Gemeinschaftsgelder"
    ],
    "de_example_1": "Die Schule wurde mit öffentlichen Geldern gebaut.",
    "de_example_fa_1": "مدرسه با پول‌های عمومی ساخته شد.",
    "de_example_2": "Öffentliche Gelder müssen sinnvoll verwendet werden.",
    "de_example_fa_2": "پول‌های عمومی باید به‌درستی استفاده شوند.",
    "fa_meaning": "پول‌های عمومی",
    "en_meaning": "public funds",
    "part_of_speech": "Substantiv",
    "article": "die",
    "frequency": "Very common",
    "cefr_level": "B1",
    "perfekt_präteritum": "",
    "is_verb": false,
    "word": "öffentliche Gelder",
    "word_query": "öffentliche Gelder"
}