{
    "de_meaning": "Wenn man überzeugt ist, glaubt man fest, dass etwas richtig oder wahr ist.",
    "de_meaning_fa": "وقتی کسی قانع است، محکم باور دارد که چیزی درست یا صحیح است.",
    "de_synonyms": [
        "fest glauben",
        "sicher sein",
        "keine Zweifel haben"
    ],
    "de_example_1": "Ich bin überzeugt, dass du das schaffst.",
    "de_example_fa_1": "من مطمئنم که تو موفق می‌شوی.",
    "de_example_2": "Sie ist überzeugt, die richtige Entscheidung getroffen zu haben.",
    "de_example_fa_2": "او مطمئن است که تصمیم درستی گرفته است.",
    "fa_meaning": "قانع بودن، مطمئن بودن",
    "en_meaning": "to be convinced, to be sure",
    "part_of_speech": "Verb",
    "article": "",
    "frequency": "Very common",
    "cefr_level": "B1",
    "perfekt_präteritum": "sein + überzeugt gewesen / war überzeugt",
    "is_verb": true,
    "word": "überzeugt sein",
    "word_query": "überzeugt sein"
}