{
    "de_meaning": "Berufsorientiert bedeutet, dass etwas mit dem Beruf oder der Arbeit zu tun hat oder darauf vorbereitet.",
    "de_meaning_fa": "برفس‌اورینتیرت یعنی چیزی که مربوط به شغل یا کار باشد یا برای آن آماده کند.",
    "de_synonyms": [
        "arbeitsbezogen",
        "fachbezogen",
        "praxisorientiert"
    ],
    "de_example_1": "Der Kurs ist berufsorientiert und hilft beim Einstieg ins Arbeitsleben.",
    "de_example_fa_1": "این دوره برفس‌اورینتیرت است و به ورود به بازار کار کمک می‌کند.",
    "de_example_2": "Viele Schulen bieten heute berufsorientierte Fächer an.",
    "de_example_fa_2": "امروزه بسیاری از مدارس دروس برفس‌اورینتیرت ارائه می‌دهند.",
    "fa_meaning": "شغلی، مرتبط با شغل یا کاریابی",
    "en_meaning": "career-oriented, related to a profession or job preparation",
    "part_of_speech": "Adjektiv",
    "article": "",
    "frequency": "Fairly common",
    "cefr_level": "B1",
    "perfekt_präteritum": "",
    "is_verb": false,
    "word": "berufsorientiert",
    "word_query": "berufsorientiert"
}