{
    "de_meaning": "Eine Gliederung ist eine Liste oder ein Plan, der zeigt, wie ein Text oder ein Thema in verschiedene Teile aufgeteilt ist.",
    "de_meaning_fa": "یک گلیدرونگ فهرست یا برنامه‌ای است که نشان می‌دهد یک متن یا موضوع چگونه به بخش‌های مختلف تقسیم شده است.",
    "de_synonyms": [
        "Struktur",
        "Aufbau",
        "Übersicht"
    ],
    "de_example_1": "Die Gliederung hilft mir, meinen Aufsatz besser zu schreiben.",
    "de_example_fa_1": "گلیدرونگ به من کمک می‌کند مقاله‌ام را بهتر بنویسم.",
    "de_example_2": "Für die Präsentation brauche ich eine gute Gliederung.",
    "de_example_fa_2": "برای ارائه به یک گلیدرونگ خوب نیاز دارم.",
    "fa_meaning": "ساختار، فهرست‌بندی، تقسیم‌بندی",
    "en_meaning": "outline, structure, or organization (of a text or topic)",
    "part_of_speech": "Substantiv",
    "article": "die",
    "frequency": "Very common",
    "cefr_level": "B1",
    "perfekt_präteritum": "",
    "is_verb": false,
    "word": "die Gliederung, -en",
    "word_query": "die Gliederung",
    "word_query_expanded": "die Gliederung"
}