{
    "de_meaning": "Wenn viele Autos auf der Straße sind und sie sich nicht oder nur sehr langsam bewegen, dann steht man im Stau.",
    "de_meaning_fa": "وقتی تعداد زیادی ماشین در جاده هستند و آن‌ها حرکت نمی‌کنند یا خیلی آهسته حرکت می‌کنند، شما در ترافیک گیر کرده‌اید.",
    "de_synonyms": [
        "im Verkehr feststecken",
        "im Verkehrsstau stehen",
        "im stockenden Verkehr sein"
    ],
    "de_example_1": "Jeden Morgen muss ich im Stau stehen, wenn ich zur Arbeit fahre.",
    "de_example_fa_1": "هر روز صبح وقتی به سر کار می‌روم، در ترافیک گیر می‌کنم.",
    "de_example_2": "Wir standen gestern eine Stunde lang im Stau.",
    "de_example_fa_2": "ما دیروز یک ساعت در ترافیک گیر کردیم.",
    "fa_meaning": "در ترافیک گیر کردن",
    "en_meaning": "to be stuck in traffic",
    "part_of_speech": "Redewendung (Verb)",
    "article": "",
    "frequency": "Very common",
    "cefr_level": "A2",
    "perfekt_präteritum": "haben + im Stau gestanden / stand im Stau",
    "is_verb": true,
    "word": "im Stau stehen",
    "word_query": "im Stau stehen",
    "word_query_expanded": "im Stau stehen"
}