{
    "de_meaning": "Sich vorbeugen bedeutet, den Oberkörper nach vorne zu bewegen.",
    "de_meaning_fa": "خم شدن به جلو یعنی بدن خود را به سمت جلو حرکت دادن.",
    "de_synonyms": [
        "sich nach vorne beugen",
        "sich bücken",
        "sich neigen"
    ],
    "de_example_1": "Bitte beim Sitzen nicht zu weit nach vorne vorbeugen.",
    "de_example_fa_1": "لطفاً هنگام نشستن زیاد به جلو خم نشوید.",
    "de_example_2": "Er musste sich vorbeugen, um das Buch aufzuheben.",
    "de_example_fa_2": "او مجبور شد برای برداشتن کتاب خم شود.",
    "fa_meaning": "خم شدن به جلو",
    "en_meaning": "to bend forward",
    "part_of_speech": "Verb",
    "article": "",
    "frequency": "Fairly common",
    "cefr_level": "B1",
    "perfekt_präteritum": "hat sich vorgebeugt / beugte sich vor",
    "is_verb": true,
    "word": "sich vorbeugen",
    "word_query": "sich vorbeugen"
}